specpie/__init__.py
specpie/descriptors.py
specpie/fake.py
specpie/fake_decorator.py
specpie/printer.py
specpie/spec.py
specpie-1.3.4.data/scripts/specpie
specpie-1.3.4.dist-info/DESCRIPTION.rst
specpie-1.3.4.dist-info/METADATA
specpie-1.3.4.dist-info/RECORD
specpie-1.3.4.dist-info/WHEEL
specpie-1.3.4.dist-info/metadata.json
specpie-1.3.4.dist-info/top_level.txt
