Metadata-Version: 2.0
Name: specpie
Version: 1.3.4
Summary: A BDD-like test framework
Home-page: https://github.com/mralves/specpie
Author: mralves
Author-email: mateusra@id.uff.br
License: MIT License
Keywords: test bdd
Platform: UNKNOWN
Requires-Dist: colorama
Requires-Dist: coverage
